qiskit_addon_pna/__init__.py
qiskit_addon_pna/pna.py
qiskit_addon_pna-0.2.0.dist-info/METADATA
qiskit_addon_pna-0.2.0.dist-info/WHEEL
qiskit_addon_pna-0.2.0.dist-info/licenses/LICENSE.txt
qiskit_addon_pna-0.2.0.dist-info/RECORD
