Metadata-Version: 2.4
Name: qiskit-addon-pna
Version: 0.2.0
Summary: Mitigate a global noise channel by propagating an observable through the anti-noise.
License:                     Copyright 2024 IBM and its contributors
License-File: LICENSE.txt
Classifier: Intended Audience :: Developers
Classifier: Intended Audience :: Science/Research
Classifier: License :: OSI Approved :: Apache Software License
Classifier: Natural Language :: English
Classifier: Operating System :: POSIX :: Linux
Classifier: Programming Language :: Python :: 3.10
Classifier: Programming Language :: Python :: 3.11
Classifier: Programming Language :: Python :: 3.12
Classifier: Programming Language :: Python :: 3.13
Classifier: Topic :: Scientific/Engineering :: Physics
Requires-Python: >=3.10
Requires-Dist: numpy>=1.26
Requires-Dist: pauli-prop
Requires-Dist: qiskit-aer>=0.17
Requires-Dist: qiskit<3,>=2.1.2
Requires-Dist: samplomatic>=0.12
Provides-Extra: basetest
Requires-Dist: pytest>=8.0; extra == 'basetest'
Provides-Extra: dev
Requires-Dist: jupyter-sphinx; extra == 'dev'
Requires-Dist: matplotlib; extra == 'dev'
Requires-Dist: mypy==1.18.2; extra == 'dev'
Requires-Dist: nbmake>=1.5.0; extra == 'dev'
Requires-Dist: nbqa>=1.8.5; extra == 'dev'
Requires-Dist: nbsphinx>=0.9.4; extra == 'dev'
Requires-Dist: pylatexenc; extra == 'dev'
Requires-Dist: pylint==4.0.2; extra == 'dev'
Requires-Dist: pytest>=8.0; extra == 'dev'
Requires-Dist: qiskit-ibm-runtime>=0.38; extra == 'dev'
Requires-Dist: qiskit-sphinx-theme~=2.0.0; extra == 'dev'
Requires-Dist: reno>=4.1; extra == 'dev'
Requires-Dist: ruff==0.14.3; extra == 'dev'
Requires-Dist: sphinx-autodoc-typehints; extra == 'dev'
Requires-Dist: sphinx-copybutton; extra == 'dev'
Requires-Dist: sphinx-design; extra == 'dev'
Requires-Dist: sphinx-reredirects; extra == 'dev'
Requires-Dist: toml>=0.9.6; extra == 'dev'
Requires-Dist: tox>=4.4.3; extra == 'dev'
Provides-Extra: docs
Requires-Dist: jupyter-sphinx; extra == 'docs'
Requires-Dist: matplotlib; extra == 'docs'
Requires-Dist: nbsphinx>=0.9.4; extra == 'docs'
Requires-Dist: pylatexenc; extra == 'docs'
Requires-Dist: pytest>=8.0; extra == 'docs'
Requires-Dist: qiskit-ibm-runtime>=0.38; extra == 'docs'
Requires-Dist: qiskit-sphinx-theme~=2.0.0; extra == 'docs'
Requires-Dist: reno>=4.1; extra == 'docs'
Requires-Dist: sphinx-autodoc-typehints; extra == 'docs'
Requires-Dist: sphinx-copybutton; extra == 'docs'
Requires-Dist: sphinx-design; extra == 'docs'
Requires-Dist: sphinx-reredirects; extra == 'docs'
Provides-Extra: lint
Requires-Dist: mypy==1.18.2; extra == 'lint'
Requires-Dist: nbqa>=1.8.5; extra == 'lint'
Requires-Dist: pylint==4.0.2; extra == 'lint'
Requires-Dist: reno>=4.1; extra == 'lint'
Requires-Dist: ruff==0.14.3; extra == 'lint'
Requires-Dist: toml>=0.9.6; extra == 'lint'
Provides-Extra: nbtest
Requires-Dist: nbmake>=1.5.0; extra == 'nbtest'
Requires-Dist: pytest>=8.0; extra == 'nbtest'
Provides-Extra: notebook-dependencies
Requires-Dist: matplotlib; extra == 'notebook-dependencies'
Requires-Dist: pylatexenc; extra == 'notebook-dependencies'
Requires-Dist: qiskit-ibm-runtime>=0.38; extra == 'notebook-dependencies'
Provides-Extra: style
Requires-Dist: nbqa>=1.8.5; extra == 'style'
Requires-Dist: ruff==0.14.3; extra == 'style'
Provides-Extra: test
Requires-Dist: pytest>=8.0; extra == 'test'
